rime_utils/__init__.py
rime_utils/utils.py
rime_utils/version.py
rime_utils-0.0.2.dist-info/LICENSE
rime_utils-0.0.2.dist-info/METADATA
rime_utils-0.0.2.dist-info/WHEEL
rime_utils-0.0.2.dist-info/top_level.txt
rime_utils-0.0.2.dist-info/RECORD
